flytekitplugins_chatgpt-1.11.0-py3.12-nspkg.pth
flytekitplugins/chatgpt/__init__.py
flytekitplugins/chatgpt/agent.py
flytekitplugins/chatgpt/task.py
flytekitplugins_chatgpt-1.11.0.dist-info/METADATA
flytekitplugins_chatgpt-1.11.0.dist-info/WHEEL
flytekitplugins_chatgpt-1.11.0.dist-info/entry_points.txt
flytekitplugins_chatgpt-1.11.0.dist-info/namespace_packages.txt
flytekitplugins_chatgpt-1.11.0.dist-info/top_level.txt
flytekitplugins_chatgpt-1.11.0.dist-info/RECORD
